{
    "doc": {
        "description": "",
        "tags": []
    },
    "name": "bbn\\Accounting\\Common",
    "namespace": true,
    "realName": "Common",
    "realNamespace": "bbn\\Accounting",
    "traits": [],
    "interfaces": [],
    "fileName": "\/Accounting\/Common.php",
    "startLine": 8,
    "endLine": 24,
    "numMethods": 2,
    "numProperties": 0,
    "numConstants": 0,
    "numStaticProperties": 0,
    "interfaceNames": [],
    "isInterface": false,
    "traitAliases": [],
    "isTrait": true,
    "isAbstract": false,
    "isFinal": false,
    "modifiers": 0,
    "parentClass": null,
    "isSubclassOf": false,
    "defaultProperties": [],
    "isIterable": false,
    "extensionName": false,
    "namespaceName": "bbn\\Accounting",
    "shortName": "Common",
    "contentConstructor": null,
    "methods": {
        "getCountry": {
            "name": "getCountry",
            "summary": "",
            "description": "",
            "description_parts": [],
            "class": "bbn\\Accounting\\Common",
            "filename": "\/home\/nabab\/web\/_COMPOSER\/dev\/vendor\/bbn\/bbn\/src\/bbn\/Accounting\/Common.php",
            "static": false,
            "visibility": "public",
            "final": false,
            "code": "  public function getCountry(string $code): string\n  {\n    $o = Option::getInstance();\n    return $o->fromCode($code, 'countries', 'core', 'appui');\n  }",
            "parent": false,
            "trait": false,
            "startLine": 11,
            "endLine": 15,
            "isDeprecated": false,
            "isGenerator": false,
            "isInternal": false,
            "isUserDefined": true,
            "isVariadic": false,
            "returnsReference": false,
            "numberOfParameters": 1,
            "numberOfRequiredParameters": 1,
            "shortName": "getCountry",
            "returns": [
                "string"
            ],
            "arguments": [
                {
                    "name": "code",
                    "position": 0,
                    "type": "string",
                    "type_arr": [
                        "string"
                    ],
                    "variadic": false,
                    "reference": false,
                    "required": true,
                    "has_default": false,
                    "default": "",
                    "default_name": ""
                }
            ]
        },
        "getCurrency": {
            "name": "getCurrency",
            "summary": "",
            "description": "",
            "description_parts": [],
            "class": "bbn\\Accounting\\Common",
            "filename": "\/home\/nabab\/web\/_COMPOSER\/dev\/vendor\/bbn\/bbn\/src\/bbn\/Accounting\/Common.php",
            "static": false,
            "visibility": "public",
            "final": false,
            "code": "  public function getCurrency(string $code): string\n  {\n    $o = Option::getInstance();\n    return $o->fromCode($code, 'currencies', 'core', 'appui');\n  }",
            "parent": false,
            "trait": false,
            "startLine": 18,
            "endLine": 22,
            "isDeprecated": false,
            "isGenerator": false,
            "isInternal": false,
            "isUserDefined": true,
            "isVariadic": false,
            "returnsReference": false,
            "numberOfParameters": 1,
            "numberOfRequiredParameters": 1,
            "shortName": "getCurrency",
            "returns": [
                "string"
            ],
            "arguments": [
                {
                    "name": "code",
                    "position": 0,
                    "type": "string",
                    "type_arr": [
                        "string"
                    ],
                    "variadic": false,
                    "reference": false,
                    "required": true,
                    "has_default": false,
                    "default": "",
                    "default_name": ""
                }
            ]
        }
    },
    "properties": null,
    "staticProperties": [],
    "constants": null,
    "uses": {
        "bbn\\Appui\\Option": "Option"
    },
    "dummyComments": [],
    "summary": "",
    "description": "",
    "description_parts": []
}