{
    "doc": {
        "description": "",
        "tags": []
    },
    "name": "bbn\\Appui\\Api",
    "namespace": true,
    "traits": [],
    "interfaces": [],
    "fileName": "\/home\/thomas\/domains\/apstapp.thomas.lan\/_appui\/vendor\/bbn\/bbn\/src\/bbn\/appui\/api.php",
    "startLine": 10,
    "endLine": 194,
    "contentConstructor": {
        "file": "bbn\\Appui\\Api",
        "returns": null
    },
    "methods": {
        "__construct": {
            "name": "__construct",
            "summary": "Constructor",
            "description": "*",
            "description_parts": [
                {
                    "type": "text",
                    "content": "<p>*<\/p>"
                }
            ],
            "file": "bbn\\Appui\\Api",
            "static": false,
            "visibility": "public",
            "final": false,
            "code": "function(bbn\\User $user, bbn\\Db $db, $ttl = 300)\n  {\n    if ($user->getId()) {\n      $this->db = $db;\n      $this->jwt = new Jwt();\n      $this->jwt->prepare($user->getId(), $user->getOsession('fingerprint'), $ttl);\n    }\n  }",
            "startLine": 46,
            "endLine": 53,
            "isDeprecated": false,
            "isGenerator": false,
            "isInternal": false,
            "isUserDefined": true,
            "isVariadic": false,
            "returnsReference": false,
            "numberOfParameters": 3,
            "numberOfRequiredParameters": 2,
            "returns": null,
            "parent": false,
            "arguments": [
                {
                    "name": "user",
                    "position": 0,
                    "type": "bbn\\User",
                    "required": true,
                    "has_default": false,
                    "default": "",
                    "default_name": ""
                },
                {
                    "name": "db",
                    "position": 1,
                    "type": "bbn\\Db",
                    "required": true,
                    "has_default": false,
                    "default": "",
                    "default_name": ""
                },
                {
                    "name": "ttl",
                    "position": 2,
                    "type": "int",
                    "required": false,
                    "has_default": true,
                    "default": 300,
                    "default_name": ""
                }
            ]
        },
        "register_project": {
            "name": "register_project",
            "summary": "",
            "description": "",
            "description_parts": [],
            "file": "bbn\\Appui\\Api",
            "static": false,
            "visibility": "public",
            "final": false,
            "code": "function(array $cfg)\n  {\n    if ($this->jwt) {\n      $key_out = self::_get_tmp_key(true);\n      $jwt = $this->jwt->setKey($key_out)->set(['data' => $cfg]);\n      if ($res = X::curl(\n        self::REMOTE,\n        ['action' => 'register_project', 'data' => $jwt]\n      )\n      ) {\n        $key_in = self::_get_tmp_key();\n        return $this->jwt->setKey($key_in)->get($res);\n      }\n      else {\n        throw new \\Exception(_(\"Impossible to register\"));\n      }\n    }\n    else {\n      throw new \\Exception(_(\"No JWT\"));\n    }\n  }",
            "startLine": 56,
            "endLine": 76,
            "isDeprecated": false,
            "isGenerator": false,
            "isInternal": false,
            "isUserDefined": true,
            "isVariadic": false,
            "returnsReference": false,
            "numberOfParameters": 1,
            "numberOfRequiredParameters": 1,
            "returns": [
                "array"
            ],
            "parent": false,
            "arguments": [
                {
                    "name": "cfg",
                    "position": 0,
                    "type": "array",
                    "required": true,
                    "has_default": false,
                    "default": "",
                    "default_name": ""
                }
            ]
        },
        "has_key": {
            "name": "has_key",
            "summary": "",
            "description": "",
            "description_parts": [],
            "file": "bbn\\Appui\\Api",
            "static": false,
            "visibility": "public",
            "final": false,
            "code": "function()\n  {\n    return !!$this->_get_key();\n  }",
            "startLine": 79,
            "endLine": 82,
            "isDeprecated": false,
            "isGenerator": false,
            "isInternal": false,
            "isUserDefined": true,
            "isVariadic": false,
            "returnsReference": false,
            "numberOfParameters": 0,
            "numberOfRequiredParameters": 0,
            "returns": null,
            "parent": false,
            "arguments": []
        },
        "request": {
            "name": "request",
            "summary": "",
            "description": "",
            "description_parts": [],
            "file": "bbn\\Appui\\Api",
            "static": false,
            "visibility": "public",
            "final": false,
            "code": "function($action, array $cfg = [])\n  {\n    if ($this->jwt) {\n      $key = self::_get_key(true);\n      $jwt = $this->jwt->setKey($key)->set(['data' => $cfg]);\n      if ($res = X::curl(\n        self::REMOTE.'\/'.BBN_ID_APP,\n        ['action' => $action, 'data' => $jwt]\n      )\n      ) {\n        $key = self::_get_key();\n        return $this->jwt->setKey($key)->get($res);\n      }\n      else {\n        throw new \\Exception(_(\"Impossible to send the request\"));\n      }\n    }\n    else {\n      throw new \\Exception(_(\"No JWT\"));\n    }\n  }",
            "startLine": 85,
            "endLine": 105,
            "isDeprecated": false,
            "isGenerator": false,
            "isInternal": false,
            "isUserDefined": true,
            "isVariadic": false,
            "returnsReference": false,
            "numberOfParameters": 2,
            "numberOfRequiredParameters": 1,
            "returns": [
                "array"
            ],
            "parent": false,
            "arguments": [
                {
                    "name": "action",
                    "position": 0,
                    "type": "string",
                    "required": true,
                    "has_default": false,
                    "default": "",
                    "default_name": ""
                },
                {
                    "name": "cfg",
                    "position": 1,
                    "type": "array",
                    "required": false,
                    "has_default": true,
                    "default": [],
                    "default_name": ""
                }
            ]
        },
        "get_app_info": {
            "name": "get_app_info",
            "summary": "",
            "description": "",
            "description_parts": [],
            "file": "bbn\\Appui\\Api",
            "static": false,
            "visibility": "public",
            "final": false,
            "code": "function()\n  {\n    return $this->request('app_info');\n  }",
            "startLine": 108,
            "endLine": 111,
            "isDeprecated": false,
            "isGenerator": false,
            "isInternal": false,
            "isUserDefined": true,
            "isVariadic": false,
            "returnsReference": false,
            "numberOfParameters": 0,
            "numberOfRequiredParameters": 0,
            "returns": [
                "array"
            ],
            "parent": false,
            "arguments": []
        },
        "test": {
            "name": "test",
            "summary": "Checks whether the error property has been set (so an error happened).",
            "description": "",
            "description_parts": [],
            "file": "bbn\\Models\\Cls\\Basic",
            "static": false,
            "visibility": "public",
            "final": false,
            "code": "function()\n  {\n      return false;\n    }\n    return true;\n  }",
            "startLine": 45,
            "endLine": 50,
            "isDeprecated": false,
            "isGenerator": false,
            "isInternal": false,
            "isUserDefined": true,
            "isVariadic": false,
            "returnsReference": false,
            "numberOfParameters": 0,
            "numberOfRequiredParameters": 0,
            "returns": null,
            "parent": {
                "name": "test",
                "summary": "Checks whether the error property has been set (so an error happened).",
                "description": "",
                "description_parts": [],
                "file": "bbn\\Models\\Cls\\Basic",
                "static": false,
                "visibility": "public",
                "final": false,
                "code": "function()\n  {\n      return false;\n    }\n    return true;\n  }",
                "startLine": 45,
                "endLine": 50,
                "isDeprecated": false,
                "isGenerator": false,
                "isInternal": false,
                "isUserDefined": true,
                "isVariadic": false,
                "returnsReference": false,
                "numberOfParameters": 0,
                "numberOfRequiredParameters": 0,
                "returns": null,
                "parent": false,
                "arguments": []
            },
            "arguments": []
        },
        "check": {
            "name": "check",
            "summary": "Checks whether the error property has been set (so an error happened).",
            "description": "",
            "description_parts": [],
            "file": "bbn\\Models\\Cls\\Basic",
            "static": false,
            "visibility": "public",
            "final": false,
            "code": "function()\n  {\n      return false;\n    }\n    return true;\n  }",
            "startLine": 56,
            "endLine": 61,
            "isDeprecated": false,
            "isGenerator": false,
            "isInternal": false,
            "isUserDefined": true,
            "isVariadic": false,
            "returnsReference": false,
            "numberOfParameters": 0,
            "numberOfRequiredParameters": 0,
            "returns": null,
            "parent": {
                "name": "check",
                "summary": "Checks whether the error property has been set (so an error happened).",
                "description": "",
                "description_parts": [],
                "file": "bbn\\Models\\Cls\\Basic",
                "static": false,
                "visibility": "public",
                "final": false,
                "code": "function()\n  {\n      return false;\n    }\n    return true;\n  }",
                "startLine": 56,
                "endLine": 61,
                "isDeprecated": false,
                "isGenerator": false,
                "isInternal": false,
                "isUserDefined": true,
                "isVariadic": false,
                "returnsReference": false,
                "numberOfParameters": 0,
                "numberOfRequiredParameters": 0,
                "returns": null,
                "parent": false,
                "arguments": []
            },
            "arguments": []
        },
        "get_error": {
            "name": "get_error",
            "summary": "",
            "description": "",
            "description_parts": [],
            "file": "bbn\\Models\\Cls\\Basic",
            "static": false,
            "visibility": "public",
            "final": false,
            "code": "function()\n  {\n  }",
            "startLine": 72,
            "endLine": 74,
            "isDeprecated": false,
            "isGenerator": false,
            "isInternal": false,
            "isUserDefined": true,
            "isVariadic": false,
            "returnsReference": false,
            "numberOfParameters": 0,
            "numberOfRequiredParameters": 0,
            "returns": null,
            "parent": {
                "name": "get_error",
                "summary": "",
                "description": "",
                "description_parts": [],
                "file": "bbn\\Models\\Cls\\Basic",
                "static": false,
                "visibility": "public",
                "final": false,
                "code": "function()\n  {\n  }",
                "startLine": 72,
                "endLine": 74,
                "isDeprecated": false,
                "isGenerator": false,
                "isInternal": false,
                "isUserDefined": true,
                "isVariadic": false,
                "returnsReference": false,
                "numberOfParameters": 0,
                "numberOfRequiredParameters": 0,
                "returns": null,
                "parent": false,
                "arguments": []
            },
            "arguments": []
        },
        "get_errors": {
            "name": "get_errors",
            "summary": "",
            "description": "",
            "description_parts": [],
            "file": "bbn\\Models\\Cls\\Basic",
            "static": false,
            "visibility": "public",
            "final": false,
            "code": "function()\n  {\n  }",
            "startLine": 76,
            "endLine": 78,
            "isDeprecated": false,
            "isGenerator": false,
            "isInternal": false,
            "isUserDefined": true,
            "isVariadic": false,
            "returnsReference": false,
            "numberOfParameters": 0,
            "numberOfRequiredParameters": 0,
            "returns": null,
            "parent": {
                "name": "get_errors",
                "summary": "",
                "description": "",
                "description_parts": [],
                "file": "bbn\\Models\\Cls\\Basic",
                "static": false,
                "visibility": "public",
                "final": false,
                "code": "function()\n  {\n  }",
                "startLine": 76,
                "endLine": 78,
                "isDeprecated": false,
                "isGenerator": false,
                "isInternal": false,
                "isUserDefined": true,
                "isVariadic": false,
                "returnsReference": false,
                "numberOfParameters": 0,
                "numberOfRequiredParameters": 0,
                "returns": null,
                "parent": false,
                "arguments": []
            },
            "arguments": []
        },
        "log": {
            "name": "log",
            "summary": "",
            "description": "",
            "description_parts": [],
            "file": "bbn\\Models\\Cls\\Basic",
            "static": false,
            "visibility": "public",
            "final": false,
            "code": "function()\n  {\n\t\t\t$ar = \\func_get_args();\n\t\t\t$cn = bbn\\Str::encodeFilename(str_replace('\\\\', '_', \\get_class($this)));\n\t\t\tforeach ( $ar as $a ){\n\t\t\t\tbbn\\X::log($a, $cn);\n\t\t\t}\n\t\t}\n  }",
            "startLine": 80,
            "endLine": 88,
            "isDeprecated": false,
            "isGenerator": false,
            "isInternal": false,
            "isUserDefined": true,
            "isVariadic": false,
            "returnsReference": false,
            "numberOfParameters": 0,
            "numberOfRequiredParameters": 0,
            "returns": null,
            "parent": {
                "name": "log",
                "summary": "",
                "description": "",
                "description_parts": [],
                "file": "bbn\\Models\\Cls\\Basic",
                "static": false,
                "visibility": "public",
                "final": false,
                "code": "function()\n  {\n\t\t\t$ar = \\func_get_args();\n\t\t\t$cn = bbn\\Str::encodeFilename(str_replace('\\\\', '_', \\get_class($this)));\n\t\t\tforeach ( $ar as $a ){\n\t\t\t\tbbn\\X::log($a, $cn);\n\t\t\t}\n\t\t}\n  }",
                "startLine": 80,
                "endLine": 88,
                "isDeprecated": false,
                "isGenerator": false,
                "isInternal": false,
                "isUserDefined": true,
                "isVariadic": false,
                "returnsReference": false,
                "numberOfParameters": 0,
                "numberOfRequiredParameters": 0,
                "returns": null,
                "parent": false,
                "arguments": []
            },
            "arguments": []
        },
        "__call": {
            "name": "__call",
            "summary": "",
            "description": "",
            "description_parts": [],
            "file": "bbn\\Models\\Cls\\Basic",
            "static": false,
            "visibility": "public",
            "final": false,
            "code": "function($name, $arguments)\n  {\n    $this->log([\"Wrong method used for the class $class: $name with the following arguments:\", $arguments]);\n    die(var_dump([\"Wrong method used for the class $class: $name with the following arguments:\", $arguments]));\n  }",
            "startLine": 95,
            "endLine": 99,
            "isDeprecated": false,
            "isGenerator": false,
            "isInternal": false,
            "isUserDefined": true,
            "isVariadic": false,
            "returnsReference": false,
            "numberOfParameters": 2,
            "numberOfRequiredParameters": 2,
            "returns": null,
            "parent": {
                "name": "__call",
                "summary": "",
                "description": "",
                "description_parts": [],
                "file": "bbn\\Models\\Cls\\Basic",
                "static": false,
                "visibility": "public",
                "final": false,
                "code": "function($name, $arguments)\n  {\n    $this->log([\"Wrong method used for the class $class: $name with the following arguments:\", $arguments]);\n    die(var_dump([\"Wrong method used for the class $class: $name with the following arguments:\", $arguments]));\n  }",
                "startLine": 95,
                "endLine": 99,
                "isDeprecated": false,
                "isGenerator": false,
                "isInternal": false,
                "isUserDefined": true,
                "isVariadic": false,
                "returnsReference": false,
                "numberOfParameters": 2,
                "numberOfRequiredParameters": 2,
                "returns": null,
                "parent": false,
                "arguments": [
                    {
                        "name": "name",
                        "position": 0,
                        "type": null,
                        "required": true,
                        "has_default": false,
                        "default": "",
                        "default_name": ""
                    },
                    {
                        "name": "arguments",
                        "position": 1,
                        "type": null,
                        "required": true,
                        "has_default": false,
                        "default": "",
                        "default_name": ""
                    }
                ]
            },
            "arguments": [
                {
                    "name": "name",
                    "position": 0,
                    "type": null,
                    "required": true,
                    "has_default": false,
                    "default": "",
                    "default_name": ""
                },
                {
                    "name": "arguments",
                    "position": 1,
                    "type": null,
                    "required": true,
                    "has_default": false,
                    "default": "",
                    "default_name": ""
                }
            ]
        },
        "is_debug": {
            "name": "is_debug",
            "summary": "",
            "description": "",
            "description_parts": [],
            "file": "bbn\\Models\\Cls\\Basic",
            "static": false,
            "visibility": "public",
            "final": false,
            "code": "function()\n  {\n  }",
            "startLine": 104,
            "endLine": 106,
            "isDeprecated": false,
            "isGenerator": false,
            "isInternal": false,
            "isUserDefined": true,
            "isVariadic": false,
            "returnsReference": false,
            "numberOfParameters": 0,
            "numberOfRequiredParameters": 0,
            "returns": null,
            "parent": {
                "name": "is_debug",
                "summary": "",
                "description": "",
                "description_parts": [],
                "file": "bbn\\Models\\Cls\\Basic",
                "static": false,
                "visibility": "public",
                "final": false,
                "code": "function()\n  {\n  }",
                "startLine": 104,
                "endLine": 106,
                "isDeprecated": false,
                "isGenerator": false,
                "isInternal": false,
                "isUserDefined": true,
                "isVariadic": false,
                "returnsReference": false,
                "numberOfParameters": 0,
                "numberOfRequiredParameters": 0,
                "returns": null,
                "parent": false,
                "arguments": []
            },
            "arguments": []
        },
        "set_debug": {
            "name": "set_debug",
            "summary": "",
            "description": "",
            "description_parts": [],
            "file": "bbn\\Models\\Cls\\Basic",
            "static": false,
            "visibility": "public",
            "final": false,
            "code": "function($debug)\n  {\n  }",
            "startLine": 112,
            "endLine": 114,
            "isDeprecated": false,
            "isGenerator": false,
            "isInternal": false,
            "isUserDefined": true,
            "isVariadic": false,
            "returnsReference": false,
            "numberOfParameters": 1,
            "numberOfRequiredParameters": 1,
            "returns": null,
            "parent": {
                "name": "set_debug",
                "summary": "",
                "description": "",
                "description_parts": [],
                "file": "bbn\\Models\\Cls\\Basic",
                "static": false,
                "visibility": "public",
                "final": false,
                "code": "function($debug)\n  {\n  }",
                "startLine": 112,
                "endLine": 114,
                "isDeprecated": false,
                "isGenerator": false,
                "isInternal": false,
                "isUserDefined": true,
                "isVariadic": false,
                "returnsReference": false,
                "numberOfParameters": 1,
                "numberOfRequiredParameters": 1,
                "returns": null,
                "parent": false,
                "arguments": [
                    {
                        "name": "debug",
                        "position": 0,
                        "type": "bool",
                        "required": true,
                        "has_default": false,
                        "default": "",
                        "default_name": ""
                    }
                ]
            },
            "arguments": [
                {
                    "name": "debug",
                    "position": 0,
                    "type": "bool",
                    "required": true,
                    "has_default": false,
                    "default": "",
                    "default_name": ""
                }
            ]
        }
    },
    "properties": {
        "jwt": {
            "visibility": "public"
        }
    },
    "staticProperties": {
        "_rsa_in_tmp": null,
        "_rsa_out_tmp": null,
        "_rsa_in": null,
        "_rsa_out": null,
        "_rsa_public": null
    },
    "constants": [],
    "numMethods": 13,
    "numProperties": 1,
    "numConstants": 5,
    "numStaticProperties": 5,
    "interfaceNames": [],
    "isInterface": false,
    "traitNames": [],
    "traitAliases": [],
    "isTrait": false,
    "isAbstract": false,
    "isFinal": false,
    "modifiers": 0,
    "parentClass": "bbn\\Models\\Cls\\Basic",
    "isSubclassOf": false,
    "defaultProperties": {
        "_rsa_in_tmp": null,
        "_rsa_out_tmp": null,
        "_rsa_in": null,
        "_rsa_out": null,
        "_rsa_public": null,
        "jwt": null,
        "db": null,
        "errors": [],
        "error": false,
        "debug": false,
        "log": []
    },
    "isIterable": false,
    "extensionName": false,
    "namespaceName": "bbn\\Appui",
    "shortName": "api",
    "summary": ""
}